Metadata-Version: 2.1
Name: BASC-py4chan
Version: 0.6.6
Summary: Python 4chan API Wrapper. Improved version of Edgeworth's original py-4chan wrapper.
Home-page: http://github.com/bibanon/BASC-py4chan
Author: Antonizoon Overtwater
Author-email: antonizoon@bibanon.org
License:             DO WHAT THE FUCK YOU WANT TO PUBLIC LICENSE
Keywords: 4chan api
Platform: UNKNOWN
Classifier: Intended Audience :: Developers
Classifier: Natural Language :: English
Classifier: Programming Language :: Python :: 2
Classifier: Programming Language :: Python :: 3
License-File: LICENSE
